[
  {
    "DataType": 2,
    "RecordType": 0,
    "DataAdjustment": 1,
    "DataResolution": 1,
    "UnitOfMeasure": 0,
    "Year": 2023,
    "Month": 7,
    "Value": 23.59,
    "NumberOfTimes": 1
  },
  {
    "DataType": 2,
    "RecordType": 1,
    "DataAdjustment": 1,
    "DataResolution": 1,
    "UnitOfMeasure": 0,
    "Year": 1949,
    "Month": 1,
    "Value": -2.36,
    "NumberOfTimes": 1
  },
  {
    "DataType": 2,
    "RecordType": 0,
    "DataAdjustment": 0,
    "DataResolution": 1,
    "UnitOfMeasure": 0,
    "Year": 2023,
    "Month": 7,
    "Value": 23.99,
    "NumberOfTimes": 1
  },
  {
    "DataType": 2,
    "RecordType": 1,
    "DataAdjustment": 0,
    "DataResolution": 1,
    "UnitOfMeasure": 0,
    "Year": 1949,
    "Month": 1,
    "Value": -1.89,
    "NumberOfTimes": 1
  },
  {
    "DataType": 3,
    "RecordType": 0,
    "DataResolution": 1,
    "UnitOfMeasure": 2,
    "Year": 1955,
    "Month": 7,
    "Value": 247.8,
    "NumberOfTimes": 1
  },
  {
    "DataType": 3,
    "RecordType": 1,
    "DataResolution": 1,
    "UnitOfMeasure": 2,
    "Year": 1915,
    "Month": 6,
    "Value": 0,
    "NumberOfTimes": 94
  },
  {
    "DataType": 0,
    "RecordType": 0,
    "DataAdjustment": 0,
    "DataResolution": 3,
    "UnitOfMeasure": 0,
    "Year": 1940,
    "Month": 7,
    "Day": 14,
    "Value": 38.3,
    "NumberOfTimes": 1
  },
  {
    "DataType": 0,
    "RecordType": 1,
    "DataAdjustment": 0,
    "DataResolution": 3,
    "UnitOfMeasure": 0,
    "Year": 1962,
    "Month": 1,
    "Day": 11,
    "Value": -11.7,
    "NumberOfTimes": 1
  },
  {
    "DataType": 1,
    "RecordType": 0,
    "DataAdjustment": 0,
    "DataResolution": 3,
    "UnitOfMeasure": 0,
    "Year": 2009,
    "Month": 7,
    "Day": 10,
    "Value": 26.1,
    "NumberOfTimes": 1
  },
  {
    "DataType": 1,
    "RecordType": 1,
    "DataAdjustment": 0,
    "DataResolution": 3,
    "UnitOfMeasure": 0,
    "Year": 1933,
    "Month": 2,
    "Day": 7,
    "Value": -23.3,
    "NumberOfTimes": 1
  },
  {
    "DataType": 3,
    "RecordType": 0,
    "DataResolution": 3,
    "UnitOfMeasure": 2,
    "Year": 1936,
    "Month": 9,
    "Day": 26,
    "Value": 96.5,
    "NumberOfTimes": 1
  },
  {
    "DataType": 3,
    "RecordType": 1,
    "DataResolution": 3,
    "UnitOfMeasure": 2,
    "Year": 1912,
    "Month": 2,
    "Day": 1,
    "Value": 0,
    "NumberOfTimes": 30582
  }
]