[
  {
    "DataType": 2,
    "RecordType": 0,
    "DataAdjustment": 1,
    "DataResolution": 1,
    "UnitOfMeasure": 0,
    "Year": 2021,
    "Month": 7,
    "Value": 25.31,
    "NumberOfTimes": 1
  },
  {
    "DataType": 2,
    "RecordType": 1,
    "DataAdjustment": 1,
    "DataResolution": 1,
    "UnitOfMeasure": 0,
    "Year": 1937,
    "Month": 1,
    "Value": -3.37,
    "NumberOfTimes": 1
  },
  {
    "DataType": 2,
    "RecordType": 0,
    "DataAdjustment": 0,
    "DataResolution": 1,
    "UnitOfMeasure": 0,
    "Year": 2021,
    "Month": 7,
    "Value": 25.35,
    "NumberOfTimes": 1
  },
  {
    "DataType": 2,
    "RecordType": 1,
    "DataAdjustment": 0,
    "DataResolution": 1,
    "UnitOfMeasure": 0,
    "Year": 1937,
    "Month": 1,
    "Value": -4.04,
    "NumberOfTimes": 1
  },
  {
    "DataType": 3,
    "RecordType": 0,
    "DataResolution": 1,
    "UnitOfMeasure": 2,
    "Year": 1955,
    "Month": 12,
    "Value": 666.3,
    "NumberOfTimes": 1
  },
  {
    "DataType": 3,
    "RecordType": 1,
    "DataResolution": 1,
    "UnitOfMeasure": 2,
    "Year": 1911,
    "Month": 8,
    "Value": 0,
    "NumberOfTimes": 139
  },
  {
    "DataType": 0,
    "RecordType": 0,
    "DataAdjustment": 0,
    "DataResolution": 3,
    "UnitOfMeasure": 0,
    "Year": 1917,
    "Month": 9,
    "Day": 3,
    "Value": 41.1,
    "NumberOfTimes": 1
  },
  {
    "DataType": 0,
    "RecordType": 1,
    "DataAdjustment": 0,
    "DataResolution": 3,
    "UnitOfMeasure": 0,
    "Year": 1990,
    "Month": 12,
    "Day": 29,
    "Value": -7.2,
    "NumberOfTimes": 1
  },
  {
    "DataType": 1,
    "RecordType": 0,
    "DataAdjustment": 0,
    "DataResolution": 3,
    "UnitOfMeasure": 0,
    "Year": 2009,
    "Month": 6,
    "Day": 19,
    "Value": 27.8,
    "NumberOfTimes": 1
  },
  {
    "DataType": 1,
    "RecordType": 1,
    "DataAdjustment": 0,
    "DataResolution": 3,
    "UnitOfMeasure": 0,
    "Year": 1912,
    "Month": 1,
    "Day": 3,
    "Value": -19.4,
    "NumberOfTimes": 1
  },
  {
    "DataType": 3,
    "RecordType": 0,
    "DataResolution": 3,
    "UnitOfMeasure": 2,
    "Year": 1950,
    "Month": 11,
    "Day": 19,
    "Value": 171.2,
    "NumberOfTimes": 1
  },
  {
    "DataType": 3,
    "RecordType": 1,
    "DataResolution": 3,
    "UnitOfMeasure": 2,
    "Year": 1911,
    "Month": 1,
    "Day": 1,
    "Value": 0,
    "NumberOfTimes": 28968
  }
]