[
  {
    "DataType": 2,
    "RecordType": 0,
    "DataAdjustment": 1,
    "DataResolution": 1,
    "UnitOfMeasure": 0,
    "Year": 2023,
    "Month": 7,
    "Value": 25,
    "NumberOfTimes": 1
  },
  {
    "DataType": 2,
    "RecordType": 1,
    "DataAdjustment": 1,
    "DataResolution": 1,
    "UnitOfMeasure": 0,
    "Year": 1969,
    "Month": 1,
    "Value": -29.72,
    "NumberOfTimes": 1
  },
  {
    "DataType": 2,
    "RecordType": 0,
    "DataAdjustment": 0,
    "DataResolution": 1,
    "UnitOfMeasure": 0,
    "Year": 2023,
    "Month": 7,
    "Value": 25,
    "NumberOfTimes": 1
  },
  {
    "DataType": 2,
    "RecordType": 1,
    "DataAdjustment": 0,
    "DataResolution": 1,
    "UnitOfMeasure": 0,
    "Year": 1969,
    "Month": 1,
    "Value": -29.72,
    "NumberOfTimes": 1
  },
  {
    "DataType": 3,
    "RecordType": 0,
    "DataResolution": 1,
    "UnitOfMeasure": 2,
    "Year": 1962,
    "Month": 8,
    "Value": 164.9,
    "NumberOfTimes": 1
  },
  {
    "DataType": 3,
    "RecordType": 1,
    "DataResolution": 1,
    "UnitOfMeasure": 2,
    "Year": 1902,
    "Month": 3,
    "Value": 0,
    "NumberOfTimes": 4
  },
  {
    "DataType": 0,
    "RecordType": 0,
    "DataAdjustment": 0,
    "DataResolution": 3,
    "UnitOfMeasure": 0,
    "Year": 1936,
    "Month": 7,
    "Day": 22,
    "Value": 41.6,
    "NumberOfTimes": 1
  },
  {
    "DataType": 0,
    "RecordType": 1,
    "DataAdjustment": 0,
    "DataResolution": 3,
    "UnitOfMeasure": 0,
    "Year": 1929,
    "Month": 12,
    "Day": 12,
    "Value": -39.2,
    "NumberOfTimes": 1
  },
  {
    "DataType": 1,
    "RecordType": 0,
    "DataAdjustment": 0,
    "DataResolution": 3,
    "UnitOfMeasure": 0,
    "Year": 1998,
    "Month": 7,
    "Day": 15,
    "Value": 24,
    "NumberOfTimes": 1
  },
  {
    "DataType": 1,
    "RecordType": 1,
    "DataAdjustment": 0,
    "DataResolution": 3,
    "UnitOfMeasure": 0,
    "Year": 1943,
    "Month": 1,
    "Day": 18,
    "Value": -44.9,
    "NumberOfTimes": 1
  },
  {
    "DataType": 3,
    "RecordType": 0,
    "DataResolution": 3,
    "UnitOfMeasure": 2,
    "Year": 1892,
    "Month": 1,
    "Day": 21,
    "Value": 96,
    "NumberOfTimes": 1
  },
  {
    "DataType": 3,
    "RecordType": 1,
    "DataResolution": 3,
    "UnitOfMeasure": 2,
    "Year": 1881,
    "Month": 1,
    "Day": 1,
    "Value": 0,
    "NumberOfTimes": 28341
  }
]