[
  {
    "DataType": 2,
    "RecordType": 0,
    "DataAdjustment": 1,
    "DataResolution": 1,
    "UnitOfMeasure": 0,
    "Year": 1999,
    "Month": 8,
    "Value": 39.4,
    "NumberOfTimes": 1
  },
  {
    "DataType": 2,
    "RecordType": 1,
    "DataAdjustment": 1,
    "DataResolution": 1,
    "UnitOfMeasure": 0,
    "Year": 1989,
    "Month": 1,
    "Value": 17.41,
    "NumberOfTimes": 1
  },
  {
    "DataType": 2,
    "RecordType": 0,
    "DataAdjustment": 0,
    "DataResolution": 1,
    "UnitOfMeasure": 0,
    "Year": 2017,
    "Month": 7,
    "Value": 39.05,
    "NumberOfTimes": 1
  },
  {
    "DataType": 2,
    "RecordType": 1,
    "DataAdjustment": 0,
    "DataResolution": 1,
    "UnitOfMeasure": 0,
    "Year": 2023,
    "Month": 9,
    "Value": 9.6,
    "NumberOfTimes": 1
  },
  {
    "DataType": 3,
    "RecordType": 0,
    "DataResolution": 1,
    "UnitOfMeasure": 2,
    "Year": 1988,
    "Month": 2,
    "Value": 202.3,
    "NumberOfTimes": 1
  },
  {
    "DataType": 3,
    "RecordType": 1,
    "DataResolution": 1,
    "UnitOfMeasure": 2,
    "Year": 1982,
    "Month": 1,
    "Value": 0,
    "NumberOfTimes": 324
  },
  {
    "DataType": 3,
    "RecordType": 0,
    "DataResolution": 3,
    "UnitOfMeasure": 2,
    "Year": 1997,
    "Month": 3,
    "Day": 9,
    "Value": 132.1,
    "NumberOfTimes": 1
  },
  {
    "DataType": 3,
    "RecordType": 1,
    "DataResolution": 3,
    "UnitOfMeasure": 2,
    "Year": 1997,
    "Month": 1,
    "Day": 1,
    "Value": 0,
    "NumberOfTimes": 613
  }
]