[
  {
    "DataType": 2,
    "RecordType": 0,
    "DataAdjustment": 1,
    "DataResolution": 1,
    "UnitOfMeasure": 0,
    "Year": 2023,
    "Month": 7,
    "Value": 31.8,
    "NumberOfTimes": 1
  },
  {
    "DataType": 2,
    "RecordType": 1,
    "DataAdjustment": 1,
    "DataResolution": 1,
    "UnitOfMeasure": 0,
    "Year": 1960,
    "Month": 12,
    "Value": 0.89,
    "NumberOfTimes": 1
  },
  {
    "DataType": 2,
    "RecordType": 0,
    "DataAdjustment": 0,
    "DataResolution": 1,
    "UnitOfMeasure": 0,
    "Year": 2023,
    "Month": 7,
    "Value": 31.87,
    "NumberOfTimes": 1
  },
  {
    "DataType": 2,
    "RecordType": 1,
    "DataAdjustment": 0,
    "DataResolution": 1,
    "UnitOfMeasure": 0,
    "Year": 1960,
    "Month": 12,
    "Value": 0.58,
    "NumberOfTimes": 1
  },
  {
    "DataType": 3,
    "RecordType": 0,
    "DataResolution": 1,
    "UnitOfMeasure": 2,
    "Year": 1942,
    "Month": 8,
    "Value": 155.2,
    "NumberOfTimes": 1
  },
  {
    "DataType": 3,
    "RecordType": 1,
    "DataResolution": 1,
    "UnitOfMeasure": 2,
    "Year": 1909,
    "Month": 1,
    "Value": 0,
    "NumberOfTimes": 193
  },
  {
    "DataType": 0,
    "RecordType": 0,
    "DataAdjustment": 0,
    "DataResolution": 3,
    "UnitOfMeasure": 0,
    "Year": 1994,
    "Month": 6,
    "Day": 26,
    "Value": 43.9,
    "NumberOfTimes": 2
  },
  {
    "DataType": 0,
    "RecordType": 1,
    "DataAdjustment": 0,
    "DataResolution": 3,
    "UnitOfMeasure": 0,
    "Year": 2011,
    "Month": 2,
    "Day": 2,
    "Value": -12.2,
    "NumberOfTimes": 1
  },
  {
    "DataType": 1,
    "RecordType": 0,
    "DataAdjustment": 0,
    "DataResolution": 3,
    "UnitOfMeasure": 0,
    "Year": 1918,
    "Month": 7,
    "Day": 19,
    "Value": 33.9,
    "NumberOfTimes": 1
  },
  {
    "DataType": 1,
    "RecordType": 1,
    "DataAdjustment": 0,
    "DataResolution": 3,
    "UnitOfMeasure": 0,
    "Year": 1962,
    "Month": 1,
    "Day": 11,
    "Value": -21.7,
    "NumberOfTimes": 1
  },
  {
    "DataType": 3,
    "RecordType": 0,
    "DataResolution": 3,
    "UnitOfMeasure": 2,
    "Year": 1979,
    "Month": 9,
    "Day": 15,
    "Value": 67.1,
    "NumberOfTimes": 1
  },
  {
    "DataType": 3,
    "RecordType": 1,
    "DataResolution": 3,
    "UnitOfMeasure": 2,
    "Year": 1909,
    "Month": 1,
    "Day": 1,
    "Value": 0,
    "NumberOfTimes": 32115
  }
]