[
  {
    "DataType": 2,
    "RecordType": 0,
    "DataAdjustment": 1,
    "DataResolution": 1,
    "UnitOfMeasure": 0,
    "Year": 1928,
    "Month": 7,
    "Value": 24.56,
    "NumberOfTimes": 1
  },
  {
    "DataType": 2,
    "RecordType": 1,
    "DataAdjustment": 1,
    "DataResolution": 1,
    "UnitOfMeasure": 0,
    "Year": 1893,
    "Month": 1,
    "Value": -10.49,
    "NumberOfTimes": 1
  },
  {
    "DataType": 2,
    "RecordType": 0,
    "DataAdjustment": 0,
    "DataResolution": 1,
    "UnitOfMeasure": 0,
    "Year": 1890,
    "Month": 8,
    "Value": 25.4,
    "NumberOfTimes": 1
  },
  {
    "DataType": 2,
    "RecordType": 1,
    "DataAdjustment": 0,
    "DataResolution": 1,
    "UnitOfMeasure": 0,
    "Year": 1893,
    "Month": 1,
    "Value": -10,
    "NumberOfTimes": 1
  }
]