[
  {
    "DataType": 2,
    "RecordType": 0,
    "DataAdjustment": 1,
    "DataResolution": 1,
    "UnitOfMeasure": 0,
    "Year": 2003,
    "Month": 8,
    "Value": 27.74,
    "NumberOfTimes": 1
  },
  {
    "DataType": 2,
    "RecordType": 1,
    "DataAdjustment": 1,
    "DataResolution": 1,
    "UnitOfMeasure": 0,
    "Year": 1985,
    "Month": 1,
    "Value": 4.43,
    "NumberOfTimes": 1
  },
  {
    "DataType": 2,
    "RecordType": 0,
    "DataAdjustment": 0,
    "DataResolution": 1,
    "UnitOfMeasure": 0,
    "Year": 2003,
    "Month": 8,
    "Value": 27.45,
    "NumberOfTimes": 1
  },
  {
    "DataType": 2,
    "RecordType": 1,
    "DataAdjustment": 0,
    "DataResolution": 1,
    "UnitOfMeasure": 0,
    "Year": 1830,
    "Month": 1,
    "Value": 3.5,
    "NumberOfTimes": 1
  },
  {
    "DataType": 0,
    "RecordType": 0,
    "DataAdjustment": 0,
    "DataResolution": 3,
    "UnitOfMeasure": 0,
    "Year": 2001,
    "Month": 8,
    "Day": 4,
    "Value": 32.4,
    "NumberOfTimes": 1
  },
  {
    "DataType": 0,
    "RecordType": 1,
    "DataAdjustment": 0,
    "DataResolution": 3,
    "UnitOfMeasure": 0,
    "Year": 1976,
    "Month": 3,
    "Day": 8,
    "Value": 6,
    "NumberOfTimes": 1
  },
  {
    "DataType": 1,
    "RecordType": 0,
    "DataAdjustment": 0,
    "DataResolution": 3,
    "UnitOfMeasure": 0,
    "Year": 2001,
    "Month": 7,
    "Day": 30,
    "Value": 23.8,
    "NumberOfTimes": 1
  },
  {
    "DataType": 1,
    "RecordType": 1,
    "DataAdjustment": 0,
    "DataResolution": 3,
    "UnitOfMeasure": 0,
    "Year": 2000,
    "Month": 1,
    "Day": 26,
    "Value": -0.1,
    "NumberOfTimes": 2
  },
  {
    "DataType": 3,
    "RecordType": 0,
    "DataResolution": 3,
    "UnitOfMeasure": 2,
    "Year": 1993,
    "Month": 8,
    "Day": 24,
    "Value": 257,
    "NumberOfTimes": 1
  },
  {
    "DataType": 3,
    "RecordType": 1,
    "DataResolution": 3,
    "UnitOfMeasure": 2,
    "Year": 1973,
    "Month": 1,
    "Day": 5,
    "Value": 0,
    "NumberOfTimes": 11971
  }
]