[
  {
    "DataType": 2,
    "RecordType": 0,
    "DataAdjustment": 1,
    "DataResolution": 3,
    "UnitOfMeasure": 0,
    "Year": 2009,
    "Month": 1,
    "Day": 30,
    "Value": 30.1,
    "NumberOfTimes": 1
  },
  {
    "DataType": 2,
    "RecordType": 1,
    "DataAdjustment": 1,
    "DataResolution": 3,
    "UnitOfMeasure": 0,
    "Year": 1943,
    "Month": 7,
    "Day": 8,
    "Value": -0.6,
    "NumberOfTimes": 1
  },
  {
    "DataType": 0,
    "RecordType": 0,
    "DataAdjustment": 1,
    "DataResolution": 3,
    "UnitOfMeasure": 0,
    "Year": 2009,
    "Month": 1,
    "Day": 30,
    "Value": 40.4,
    "NumberOfTimes": 1
  },
  {
    "DataType": 0,
    "RecordType": 1,
    "DataAdjustment": 1,
    "DataResolution": 3,
    "UnitOfMeasure": 0,
    "Year": 1910,
    "Month": 7,
    "Day": 2,
    "Value": 4,
    "NumberOfTimes": 1
  },
  {
    "DataType": 1,
    "RecordType": 0,
    "DataAdjustment": 1,
    "DataResolution": 3,
    "UnitOfMeasure": 0,
    "Year": 1941,
    "Month": 2,
    "Day": 23,
    "Value": 20.4,
    "NumberOfTimes": 2
  },
  {
    "DataType": 1,
    "RecordType": 1,
    "DataAdjustment": 1,
    "DataResolution": 3,
    "UnitOfMeasure": 0,
    "Year": 1944,
    "Month": 6,
    "Day": 27,
    "Value": -8,
    "NumberOfTimes": 2
  },
  {
    "DataType": 2,
    "RecordType": 0,
    "DataAdjustment": 0,
    "DataResolution": 3,
    "UnitOfMeasure": 0,
    "Year": 2009,
    "Month": 1,
    "Day": 30,
    "Value": 30.05,
    "NumberOfTimes": 1
  },
  {
    "DataType": 2,
    "RecordType": 1,
    "DataAdjustment": 0,
    "DataResolution": 3,
    "UnitOfMeasure": 0,
    "Year": 1983,
    "Month": 6,
    "Day": 30,
    "Value": 0.35,
    "NumberOfTimes": 1
  },
  {
    "DataType": 0,
    "RecordType": 0,
    "DataAdjustment": 0,
    "DataResolution": 3,
    "UnitOfMeasure": 0,
    "Year": 2009,
    "Month": 1,
    "Day": 30,
    "Value": 40.4,
    "NumberOfTimes": 1
  },
  {
    "DataType": 0,
    "RecordType": 1,
    "DataAdjustment": 0,
    "DataResolution": 3,
    "UnitOfMeasure": 0,
    "Year": 1943,
    "Month": 7,
    "Day": 8,
    "Value": 3.8,
    "NumberOfTimes": 1
  },
  {
    "DataType": 1,
    "RecordType": 0,
    "DataAdjustment": 0,
    "DataResolution": 3,
    "UnitOfMeasure": 0,
    "Year": 1920,
    "Month": 12,
    "Day": 25,
    "Value": 21,
    "NumberOfTimes": 1
  },
  {
    "DataType": 1,
    "RecordType": 1,
    "DataAdjustment": 0,
    "DataResolution": 3,
    "UnitOfMeasure": 0,
    "Year": 1972,
    "Month": 6,
    "Day": 24,
    "Value": -7.1,
    "NumberOfTimes": 1
  },
  {
    "DataType": 3,
    "RecordType": 0,
    "DataResolution": 3,
    "UnitOfMeasure": 2,
    "Year": 1897,
    "Month": 5,
    "Day": 17,
    "Value": 93.7,
    "NumberOfTimes": 1
  },
  {
    "DataType": 3,
    "RecordType": 1,
    "DataResolution": 3,
    "UnitOfMeasure": 2,
    "Year": 1884,
    "Month": 1,
    "Day": 9,
    "Value": 0,
    "NumberOfTimes": 27644
  },
  {
    "DataType": 4,
    "RecordType": 0,
    "DataResolution": 3,
    "UnitOfMeasure": 6,
    "Year": 1996,
    "Month": 12,
    "Day": 23,
    "Value": 35.4,
    "NumberOfTimes": 2
  },
  {
    "DataType": 4,
    "RecordType": 1,
    "DataResolution": 3,
    "UnitOfMeasure": 6,
    "Year": 1992,
    "Month": 10,
    "Day": 9,
    "Value": 0.1,
    "NumberOfTimes": 2
  }
]